<annotation><filename>2024_08_84.tif</filename><size><width>4325</width><height>4325</height><depth>3</depth></size><object><name>tree</name><bndbox><xmin>882</xmin><ymin>616</ymin><xmax>1035</xmax><ymax>747</ymax></bndbox></object><object><name>tree</name><bndbox><xmin>467</xmin><ymin>961</ymin><xmax>649</xmax><ymax>1166</ymax></bndbox></object><object><name>tree</name><bndbox><xmin>431</xmin><ymin>1227</ymin><xmax>590</xmax><ymax>1361</ymax></bndbox></object><object><name>tree</name><bndbox><xmin>735</xmin><ymin>1048</ymin><xmax>870</xmax><ymax>1242</ymax></bndbox></object><object><name>tree</name><bndbox><xmin>87</xmin><ymin>1965</ymin><xmax>230</xmax><ymax>2085</ymax></bndbox></object><object><name>tree</name><bndbox><xmin>145</xmin><ymin>2113</ymin><xmax>316</xmax><ymax>2242</ymax></bndbox></object><object><name>tree</name><bndbox><xmin>283</xmin><ymin>1496</ymin><xmax>507</xmax><ymax>1667</ymax></bndbox></object><object><name>tree</name><bndbox><xmin>19</xmin><ymin>1481</ymin><xmax>162</xmax><ymax>1601</ymax></bndbox></object><object><name>tree</name><bndbox><xmin>590</xmin><ymin>1633</ymin><xmax>719</xmax><ymax>1753</ymax></bndbox></object><object><name>tree</name><bndbox><xmin>724</xmin><ymin>1697</ymin><xmax>820</xmax><ymax>1784</ymax></bndbox></object><object><name>tree</name><bndbox><xmin>318</xmin><ymin>1860</ymin><xmax>485</xmax><ymax>2060</ymax></bndbox></object><object><name>tree</name><bndbox><xmin>285</xmin><ymin>2383</ymin><xmax>447</xmax><ymax>2513</ymax></bndbox></object><object><name>tree</name><bndbox><xmin>27</xmin><ymin>2705</ymin><xmax>196</xmax><ymax>2879</ymax></bndbox></object><object><name>tree</name><bndbox><xmin>974</xmin><ymin>1798</ymin><xmax>1090</xmax><ymax>1872</ymax></bndbox></object><object><name>tree</name><bndbox><xmin>499</xmin><ymin>1874</ymin><xmax>625</xmax><ymax>2013</ymax></bndbox></object><object><name>tree</name><bndbox><xmin>279</xmin><ymin>2614</ymin><xmax>382</xmax><ymax>2711</ymax></bndbox></object><object><name>tree</name><bndbox><xmin>338</xmin><ymin>2890</ymin><xmax>456</xmax><ymax>3004</ymax></bndbox></object><object><name>tree</name><bndbox><xmin>334</xmin><ymin>3060</ymin><xmax>413</xmax><ymax>3159</ymax></bndbox></object><object><name>tree</name><bndbox><xmin>277</xmin><ymin>3397</ymin><xmax>408</xmax><ymax>3493</ymax></bndbox></object><object><name>tree</name><bndbox><xmin>285</xmin><ymin>3274</ymin><xmax>433</xmax><ymax>3389</ymax></bndbox></object><object><name>tree</name><bndbox><xmin>174</xmin><ymin>1305</ymin><xmax>258</xmax><ymax>1400</ymax></bndbox></object><object><name>tree</name><bndbox><xmin>901</xmin><ymin>469</ymin><xmax>1016</xmax><ymax>568</ymax></bndbox></object><object><name>tree</name><bndbox><xmin>1884</xmin><ymin>1545</ymin><xmax>1985</xmax><ymax>1674</ymax></bndbox></object><object><name>tree</name><bndbox><xmin>2360</xmin><ymin>2076</ymin><xmax>2452</xmax><ymax>2195</ymax></bndbox></object><object><name>tree</name><bndbox><xmin>1999</xmin><ymin>1573</ymin><xmax>2076</xmax><ymax>1689</ymax></bndbox></object><object><name>tree</name><bndbox><xmin>2636</xmin><ymin>1476</ymin><xmax>2732</xmax><ymax>1579</ymax></bndbox></object><object><name>tree</name><bndbox><xmin>2775</xmin><ymin>1482</ymin><xmax>2902</xmax><ymax>1599</ymax></bndbox></object><object><name>tree</name><bndbox><xmin>2841</xmin><ymin>1673</ymin><xmax>2961</xmax><ymax>1848</ymax></bndbox></object><object><name>tree</name><bndbox><xmin>1687</xmin><ymin>3252</ymin><xmax>1787</xmax><ymax>3366</ymax></bndbox></object><object><name>tree</name><bndbox><xmin>1965</xmin><ymin>3662</ymin><xmax>2069</xmax><ymax>3742</ymax></bndbox></object><object><name>tree</name><bndbox><xmin>1928</xmin><ymin>3749</ymin><xmax>2043</xmax><ymax>3869</ymax></bndbox></object><object><name>tree</name><bndbox><xmin>1947</xmin><ymin>3367</ymin><xmax>2068</xmax><ymax>3499</ymax></bndbox></object><object><name>tree</name><bndbox><xmin>2101</xmin><ymin>3190</ymin><xmax>2210</xmax><ymax>3324</ymax></bndbox></object><object><name>tree</name><bndbox><xmin>2311</xmin><ymin>3917</ymin><xmax>2438</xmax><ymax>4020</ymax></bndbox></object><object><name>tree</name><bndbox><xmin>2470</xmin><ymin>3856</ymin><xmax>2573</xmax><ymax>3980</ymax></bndbox></object><object><name>tree</name><bndbox><xmin>2552</xmin><ymin>3802</ymin><xmax>2656</xmax><ymax>3903</ymax></bndbox></object><object><name>tree</name><bndbox><xmin>2383</xmin><ymin>3686</ymin><xmax>2479</xmax><ymax>3789</ymax></bndbox></object><object><name>tree</name><bndbox><xmin>2353</xmin><ymin>3373</ymin><xmax>2480</xmax><ymax>3499</ymax></bndbox></object><object><name>tree</name><bndbox><xmin>2786</xmin><ymin>4001</ymin><xmax>2897</xmax><ymax>4089</ymax></bndbox></object><object><name>tree</name><bndbox><xmin>2873</xmin><ymin>3773</ymin><xmax>2921</xmax><ymax>3829</ymax></bndbox></object><object><name>tree</name><bndbox><xmin>2818</xmin><ymin>3859</ymin><xmax>2937</xmax><ymax>3963</ymax></bndbox></object><object><name>tree</name><bndbox><xmin>2912</xmin><ymin>4009</ymin><xmax>3016</xmax><ymax>4113</ymax></bndbox></object><object><name>tree</name><bndbox><xmin>1856</xmin><ymin>3175</ymin><xmax>1942</xmax><ymax>3282</ymax></bndbox></object><object><name>tree</name><bndbox><xmin>1761</xmin><ymin>3107</ymin><xmax>1858</xmax><ymax>3240</ymax></bndbox></object><object><name>tree</name><bndbox><xmin>2407</xmin><ymin>1949</ymin><xmax>2527</xmax><ymax>2077</ymax></bndbox></object><object><name>tree</name><bndbox><xmin>2553</xmin><ymin>2239</ymin><xmax>2685</xmax><ymax>2385</ymax></bndbox></object><object><name>tree</name><bndbox><xmin>2766</xmin><ymin>2402</ymin><xmax>2894</xmax><ymax>2522</ymax></bndbox></object><object><name>tree</name><bndbox><xmin>2815</xmin><ymin>2253</ymin><xmax>2965</xmax><ymax>2390</ymax></bndbox></object><object><name>tree</name><bndbox><xmin>2936</xmin><ymin>2123</ymin><xmax>3047</xmax><ymax>2250</ymax></bndbox></object><object><name>tree</name><bndbox><xmin>2768</xmin><ymin>61</ymin><xmax>2865</xmax><ymax>152</ymax></bndbox></object><object><name>tree</name><bndbox><xmin>3828</xmin><ymin>3599</ymin><xmax>3947</xmax><ymax>3710</ymax></bndbox></object><object><name>tree</name><bndbox><xmin>3388</xmin><ymin>3806</ymin><xmax>3510</xmax><ymax>3941</ymax></bndbox></object><object><name>tree</name><bndbox><xmin>3533</xmin><ymin>4101</ymin><xmax>3634</xmax><ymax>4197</ymax></bndbox></object><object><name>tree</name><bndbox><xmin>2955</xmin><ymin>3776</ymin><xmax>3083</xmax><ymax>3890</ymax></bndbox></object><object><name>tree</name><bndbox><xmin>3125</xmin><ymin>3812</ymin><xmax>3213</xmax><ymax>3923</ymax></bndbox></object><object><name>tree</name><bndbox><xmin>4035</xmin><ymin>3135</ymin><xmax>4177</xmax><ymax>3300</ymax></bndbox></object><object><name>tree</name><bndbox><xmin>4062</xmin><ymin>3667</ymin><xmax>4202</xmax><ymax>3756</ymax></bndbox></object><object><name>tree</name><bndbox><xmin>4215</xmin><ymin>3519</ymin><xmax>4324</xmax><ymax>3665</ymax></bndbox></object><object><name>tree</name><bndbox><xmin>3938</xmin><ymin>3019</ymin><xmax>4063</xmax><ymax>3178</ymax></bndbox></object><object><name>tree</name><bndbox><xmin>3844</xmin><ymin>2739</ymin><xmax>3987</xmax><ymax>2890</ymax></bndbox></object><object><name>tree</name><bndbox><xmin>3476</xmin><ymin>2449</ymin><xmax>3590</xmax><ymax>2543</ymax></bndbox></object><object><name>tree</name><bndbox><xmin>3252</xmin><ymin>2399</ymin><xmax>3363</xmax><ymax>2519</ymax></bndbox></object><object><name>tree</name><bndbox><xmin>2992</xmin><ymin>2663</ymin><xmax>3139</xmax><ymax>2798</ymax></bndbox></object><object><name>tree</name><bndbox><xmin>3204</xmin><ymin>2234</ymin><xmax>3316</xmax><ymax>2337</ymax></bndbox></object><object><name>tree</name><bndbox><xmin>2997</xmin><ymin>2322</ymin><xmax>3123</xmax><ymax>2434</ymax></bndbox></object><object><name>tree</name><bndbox><xmin>3459</xmin><ymin>1492</ymin><xmax>3554</xmax><ymax>1582</ymax></bndbox></object><object><name>tree</name><bndbox><xmin>3512</xmin><ymin>1886</ymin><xmax>3631</xmax><ymax>1982</ymax></bndbox></object><object><name>tree</name><bndbox><xmin>3880</xmin><ymin>1821</ymin><xmax>3955</xmax><ymax>1897</ymax></bndbox></object><object><name>tree</name><bndbox><xmin>3889</xmin><ymin>1706</ymin><xmax>3986</xmax><ymax>1794</ymax></bndbox></object><object><name>tree</name><bndbox><xmin>3747</xmin><ymin>2007</ymin><xmax>3859</xmax><ymax>2116</ymax></bndbox></object><object><name>tree</name><bndbox><xmin>3930</xmin><ymin>2044</ymin><xmax>4042</xmax><ymax>2156</ymax></bndbox></object><object><name>tree</name><bndbox><xmin>3316</xmin><ymin>2499</ymin><xmax>3470</xmax><ymax>2634</ymax></bndbox></object><object><name>tree</name><bndbox><xmin>3473</xmin><ymin>2549</ymin><xmax>3553</xmax><ymax>2653</ymax></bndbox></object><object><name>tree</name><bndbox><xmin>3810</xmin><ymin>2613</ymin><xmax>3900</xmax><ymax>2735</ymax></bndbox></object><object><name>tree</name><bndbox><xmin>3978</xmin><ymin>2228</ymin><xmax>4097</xmax><ymax>2361</ymax></bndbox></object><object><name>tree</name><bndbox><xmin>4137</xmin><ymin>1839</ymin><xmax>4249</xmax><ymax>1951</ymax></bndbox></object><object><name>tree</name><bndbox><xmin>4001</xmin><ymin>1741</ymin><xmax>4124</xmax><ymax>1858</ymax></bndbox></object><object><name>tree</name><bndbox><xmin>3234</xmin><ymin>320</ymin><xmax>3368</xmax><ymax>447</ymax></bndbox></object><object><name>tree</name><bndbox><xmin>3403</xmin><ymin>413</ymin><xmax>3480</xmax><ymax>507</ymax></bndbox></object><object><name>tree</name><bndbox><xmin>3497</xmin><ymin>246</ymin><xmax>3642</xmax><ymax>381</ymax></bndbox></object><object><name>tree</name><bndbox><xmin>3044</xmin><ymin>143</ymin><xmax>3145</xmax><ymax>241</ymax></bndbox></object><object><name>tree</name><bndbox><xmin>4057</xmin><ymin>366</ymin><xmax>4200</xmax><ymax>488</ymax></bndbox></object><object><name>tree</name><bndbox><xmin>4175</xmin><ymin>3300</ymin><xmax>4314</xmax><ymax>3434</ymax></bndbox></object><object><name>tree</name><bndbox><xmin>3632</xmin><ymin>3063</ymin><xmax>3723</xmax><ymax>3158</ymax></bndbox></object><object><name>tree</name><bndbox><xmin>3033</xmin><ymin>4188</ymin><xmax>3124</xmax><ymax>4289</ymax></bndbox></object><object><name>tree</name><bndbox><xmin>3092</xmin><ymin>15</ymin><xmax>3188</xmax><ymax>104</ymax></bndbox></object><object><name>tree</name><bndbox><xmin>2937</xmin><ymin>1450</ymin><xmax>3065</xmax><ymax>1605</ymax></bndbox></object><object><name>tree</name><bndbox><xmin>3851</xmin><ymin>2335</ymin><xmax>3956</xmax><ymax>2421</ymax></bndbox></object><object><name>tree</name><bndbox><xmin>3716</xmin><ymin>2307</ymin><xmax>3825</xmax><ymax>2468</ymax></bndbox></object><object><name>tree</name><bndbox><xmin>3607</xmin><ymin>2455</ymin><xmax>3718</xmax><ymax>2566</ymax></bndbox></object><object><name>tree</name><bndbox><xmin>4206</xmin><ymin>2447</ymin><xmax>4324</xmax><ymax>2596</ymax></bndbox></object><object><name>tree</name><bndbox><xmin>4057</xmin><ymin>2691</ymin><xmax>4160</xmax><ymax>2779</ymax></bndbox></object><object><name>tree</name><bndbox><xmin>4192</xmin><ymin>3215</ymin><xmax>4277</xmax><ymax>3297</ymax></bndbox></object><object><name>tree</name><bndbox><xmin>532</xmin><ymin>1475</ymin><xmax>643</xmax><ymax>1604</ymax></bndbox></object></annotation>