<?xml version='1.0' encoding='UTF-8'?>
<annotation>
  <folder>images</folder>
  <filename>2025_02_43.tif</filename>
  <size>
    <width>4353</width>
    <height>4350</height>
    <depth>3</depth>
  </size>
  <segmented>0</segmented>
  <object>
    <name>tree</name>
    <pose>Unspecified</pose>
    <truncated>0</truncated>
    <difficult>0</difficult>
    <bndbox>
      <xmin>1528</xmin>
      <ymin>1076</ymin>
      <xmax>1702</xmax>
      <ymax>1250</ymax>
    </bndbox>
  </object>
  <object>
    <name>tree</name>
    <pose>Unspecified</pose>
    <truncated>0</truncated>
    <difficult>0</difficult>
    <bndbox>
      <xmin>1848</xmin>
      <ymin>990</ymin>
      <xmax>2059</xmax>
      <ymax>1200</ymax>
    </bndbox>
  </object>
  <object>
    <name>tree</name>
    <pose>Unspecified</pose>
    <truncated>0</truncated>
    <difficult>0</difficult>
    <bndbox>
      <xmin>1558</xmin>
      <ymin>3132</ymin>
      <xmax>1903</xmax>
      <ymax>3592</ymax>
    </bndbox>
  </object>
  <object>
    <name>tree</name>
    <pose>Unspecified</pose>
    <truncated>0</truncated>
    <difficult>0</difficult>
    <bndbox>
      <xmin>3330</xmin>
      <ymin>405</ymin>
      <xmax>3586</xmax>
      <ymax>650</ymax>
    </bndbox>
  </object>
  <object>
    <name>tree</name>
    <pose>Unspecified</pose>
    <truncated>0</truncated>
    <difficult>0</difficult>
    <bndbox>
      <xmin>3737</xmin>
      <ymin>1340</ymin>
      <xmax>3944</xmax>
      <ymax>1533</ymax>
    </bndbox>
  </object>
  <object>
    <name>tree</name>
    <pose>Unspecified</pose>
    <truncated>0</truncated>
    <difficult>0</difficult>
    <bndbox>
      <xmin>2461</xmin>
      <ymin>3579</ymin>
      <xmax>2761</xmax>
      <ymax>3874</ymax>
    </bndbox>
  </object>
  <object>
    <name>tree</name>
    <pose>Unspecified</pose>
    <truncated>0</truncated>
    <difficult>0</difficult>
    <bndbox>
      <xmin>666</xmin>
      <ymin>196</ymin>
      <xmax>801</xmax>
      <ymax>329</ymax>
    </bndbox>
  </object>
  <object>
    <name>tree</name>
    <pose>Unspecified</pose>
    <truncated>0</truncated>
    <difficult>0</difficult>
    <bndbox>
      <xmin>453</xmin>
      <ymin>2220</ymin>
      <xmax>530</xmax>
      <ymax>2293</ymax>
    </bndbox>
  </object>
  <object>
    <name>tree</name>
    <pose>Unspecified</pose>
    <truncated>0</truncated>
    <difficult>0</difficult>
    <bndbox>
      <xmin>3454</xmin>
      <ymin>900</ymin>
      <xmax>3736</xmax>
      <ymax>1132</ymax>
    </bndbox>
  </object>
  <object>
    <name>tree</name>
    <pose>Unspecified</pose>
    <truncated>0</truncated>
    <difficult>0</difficult>
    <bndbox>
      <xmin>3774</xmin>
      <ymin>561</ymin>
      <xmax>4031</xmax>
      <ymax>865</ymax>
    </bndbox>
  </object>
  <object>
    <name>tree</name>
    <pose>Unspecified</pose>
    <truncated>0</truncated>
    <difficult>0</difficult>
    <bndbox>
      <xmin>2540</xmin>
      <ymin>64</ymin>
      <xmax>2678</xmax>
      <ymax>187</ymax>
    </bndbox>
  </object>
  <object>
    <name>tree</name>
    <pose>Unspecified</pose>
    <truncated>0</truncated>
    <difficult>0</difficult>
    <bndbox>
      <xmin>2704</xmin>
      <ymin>109</ymin>
      <xmax>2802</xmax>
      <ymax>217</ymax>
    </bndbox>
  </object>
  <object>
    <name>tree</name>
    <pose>Unspecified</pose>
    <truncated>0</truncated>
    <difficult>0</difficult>
    <bndbox>
      <xmin>1008</xmin>
      <ymin>1283</ymin>
      <xmax>1197</xmax>
      <ymax>1518</ymax>
    </bndbox>
  </object>
  <object>
    <name>tree</name>
    <pose>Unspecified</pose>
    <truncated>0</truncated>
    <difficult>0</difficult>
    <bndbox>
      <xmin>3336</xmin>
      <ymin>2961</ymin>
      <xmax>3659</xmax>
      <ymax>3287</ymax>
    </bndbox>
  </object>
  <object>
    <name>tree</name>
    <pose>Unspecified</pose>
    <truncated>0</truncated>
    <difficult>0</difficult>
    <bndbox>
      <xmin>3017</xmin>
      <ymin>93</ymin>
      <xmax>3139</xmax>
      <ymax>216</ymax>
    </bndbox>
  </object>
  <object>
    <name>tree</name>
    <pose>Unspecified</pose>
    <truncated>0</truncated>
    <difficult>0</difficult>
    <bndbox>
      <xmin>3301</xmin>
      <ymin>900</ymin>
      <xmax>3399</xmax>
      <ymax>954</ymax>
    </bndbox>
  </object>
  <object>
    <name>tree</name>
    <pose>Unspecified</pose>
    <truncated>0</truncated>
    <difficult>0</difficult>
    <bndbox>
      <xmin>1171</xmin>
      <ymin>1707</ymin>
      <xmax>1529</xmax>
      <ymax>2054</ymax>
    </bndbox>
  </object>
  <object>
    <name>tree</name>
    <pose>Unspecified</pose>
    <truncated>0</truncated>
    <difficult>0</difficult>
    <bndbox>
      <xmin>3251</xmin>
      <ymin>2656</ymin>
      <xmax>3407</xmax>
      <ymax>2819</ymax>
    </bndbox>
  </object>
  <object>
    <name>tree</name>
    <pose>Unspecified</pose>
    <truncated>0</truncated>
    <difficult>0</difficult>
    <bndbox>
      <xmin>3165</xmin>
      <ymin>2700</ymin>
      <xmax>3230</xmax>
      <ymax>2756</ymax>
    </bndbox>
  </object>
</annotation>
